zimports/__init__.py
zimports/__main__.py
zimports/cli.py
zimports/zimports.py
zimports/vendored/__init__.py
zimports/vendored/flake8.py
zimports/vendored/flake8_import_order.py
zimports-0.6.3.dist-info/METADATA
zimports-0.6.3.dist-info/WHEEL
zimports-0.6.3.dist-info/entry_points.txt
zimports-0.6.3.dist-info/licenses/LICENSE
zimports-0.6.3.dist-info/RECORD
