Metadata-Version: 2.4
Name: zimports
Version: 0.6.3
Summary: Yet another import fixing tool
Project-URL: Homepage, https://github.com/sqlalchemyorg/zimports
Project-URL: Issues, https://github.com/sqlalchemyorg/zimports/issues
Author-email: Mike Bayer <mike_mp@zzzcomputing.com>
License-Expression: MIT
License-File: LICENSE
Classifier: Development Status :: 4 - Beta
Classifier: Intended Audience :: Developers
Classifier: Operating System :: OS Independent
Classifier: Programming Language :: Python :: 3
Classifier: Programming Language :: Python :: 3.9
Classifier: Programming Language :: Python :: 3.10
Classifier: Programming Language :: Python :: 3.11
Classifier: Programming Language :: Python :: 3.12
Classifier: Programming Language :: Python :: 3.13
Classifier: Programming Language :: Python :: Implementation :: CPython
Classifier: Programming Language :: Python :: Implementation :: PyPy
Requires-Python: >=3.9
Requires-Dist: flake8-import-order
Requires-Dist: importlib-metadata; python_version < '3.10'
Requires-Dist: pyflakes
Requires-Dist: tomli
